deepdata_alpha/__init__.py
deepdata_alpha/__version__.py
deepdata_alpha/deepdata_alpha.py
deepdata_alpha/dataset/__init__.py
deepdata_alpha/dataset/base.py
deepdata_alpha/dataset/data/arrhythmia/arrhythmia.csv
deepdata_alpha/dataset/data/cardio/cardio.csv
deepdata_alpha/dataset/data/dna/dna_0_179.csv
deepdata_alpha/dataset/data/letter/letter.csv
deepdata_alpha/dataset/data/letter/letter_2_class.csv
deepdata_alpha/dataset/data/mnist/mnist.csv
deepdata_alpha/dataset/data/musk/musk.csv
deepdata_alpha/dataset/data/optdigits/optdigits.csv
deepdata_alpha/dataset/data/pendigits/pendigits.csv
deepdata_alpha/dataset/data/phm/phm_RIGHT_RPhase_FB.csv
deepdata_alpha/dataset/data/phm/phm_outlier_10pct.csv
deepdata_alpha/dataset/data/phm/phm_outlier_20pct.csv
deepdata_alpha/dataset/data/phm/phm_outlier_30pct.csv
deepdata_alpha/dataset/data/phm/phm_outlier_40pct.csv
deepdata_alpha/dataset/data/pima/pima.csv
deepdata_alpha/dataset/data/satellite/satellite.csv
deepdata_alpha/dataset/data/satimage/satimage.csv
deepdata_alpha/dataset/data/shuttle/shuttle.csv
deepdata_alpha/dataset/data/speech/speech.csv
deepdata_alpha/dataset/data/usps/usps.csv
deepdata_alpha/dataset/data/vowels/vowels.csv
deepdata_alpha/model/__init__.py
deepdata_alpha/preprocess/__init__.py
deepdata_alpha/validate/__init__.py
deepdata_alpha/visualize/__init__.py
deepdata_alpha/visualize/base.py
tests/__init__.py
tests/test_deepdata_alpha.py
tests/test_lint.py
deepdata_alpha-0.2.3.dist-info/LICENSE
deepdata_alpha-0.2.3.dist-info/METADATA
deepdata_alpha-0.2.3.dist-info/NOTICE
deepdata_alpha-0.2.3.dist-info/WHEEL
deepdata_alpha-0.2.3.dist-info/top_level.txt
deepdata_alpha-0.2.3.dist-info/RECORD
