Metadata-Version: 2.1
Name: deepdata-alpha
Version: 0.2.3
Summary: The package is for developing algorithm in prediction.
Home-page: https://github.com/John/deepdata_alpha
Author: John J. H. Lin
Author-email: john.jrhunglin@gmail.com
License: UNKNOWN
Keywords: deepdata_alpha
Platform: UNKNOWN
Classifier: Development Status :: 2 - Pre-Alpha
Classifier: Intended Audience :: Developers
Classifier: Natural Language :: English
Classifier: Programming Language :: Python :: 3
Classifier: Programming Language :: Python :: 3.4
Classifier: Programming Language :: Python :: 3.5
Classifier: Programming Language :: Python :: 3.6
Provides-Extra: dev
Requires-Dist: prospector[with_pyroma]; extra == 'dev'
Requires-Dist: yapf; extra == 'dev'
Requires-Dist: isort; extra == 'dev'
